riemann.py
riemann-0.9.0.dist-info/LICENSE
riemann-0.9.0.dist-info/METADATA
riemann-0.9.0.dist-info/WHEEL
riemann-0.9.0.dist-info/top_level.txt
riemann-0.9.0.dist-info/RECORD
