Metadata-Version: 2.1
Name: riemann
Version: 0.9.0
Summary: A package for computing Riemann summations in n-dimensional space
Author-email: Jacob Lee <Jacob.J.Lee@outlook.com>
Project-URL: Homepage, https://github.com/JacobLee23/riemann
Project-URL: Documentation, https://riemann-py.readthedocs.io/en/latest/
Project-URL: Issue Tracker, https://github.com/JacobLee23/riemann/issues/
Classifier: Development Status :: 1 - Planning
Classifier: License :: OSI Approved :: MIT License
Classifier: Operating System :: OS Independent
Classifier: Programming Language :: Python
Classifier: Programming Language :: Python :: 3
Classifier: Programming Language :: Python :: 3.7
Classifier: Programming Language :: Python :: 3.8
Classifier: Programming Language :: Python :: 3.9
Classifier: Programming Language :: Python :: 3.10
Classifier: Programming Language :: Python :: 3.11
Classifier: Topic :: Scientific/Engineering :: Mathematics
Requires-Python: >=3.7
License-File: LICENSE
